remotior_sensus/COPYING
remotior_sensus/__init__.py
remotior_sensus/core/__init__.py
remotior_sensus/core/bandset_catalog.py
remotior_sensus/core/configurations.py
remotior_sensus/core/log.py
remotior_sensus/core/messages.py
remotior_sensus/core/multiprocess_manager.py
remotior_sensus/core/output_manager.py
remotior_sensus/core/processor.py
remotior_sensus/core/processor_functions.py
remotior_sensus/core/progress.py
remotior_sensus/core/session.py
remotior_sensus/core/spectral_signatures.py
remotior_sensus/core/table_manager.py
remotior_sensus/core/temporary.py
remotior_sensus/logo/remotior_sensus.svg
remotior_sensus/logo/remotior_sensus_bw.svg
remotior_sensus/tools/__init__.py
remotior_sensus/tools/band_calc.py
remotior_sensus/tools/band_classification.py
remotior_sensus/tools/band_clip.py
remotior_sensus/tools/band_clustering.py
remotior_sensus/tools/band_combination.py
remotior_sensus/tools/band_dilation.py
remotior_sensus/tools/band_erosion.py
remotior_sensus/tools/band_mask.py
remotior_sensus/tools/band_neighbor_pixels.py
remotior_sensus/tools/band_pca.py
remotior_sensus/tools/band_resample.py
remotior_sensus/tools/band_sieve.py
remotior_sensus/tools/band_spectral_distance.py
remotior_sensus/tools/band_stack.py
remotior_sensus/tools/cross_classification.py
remotior_sensus/tools/download_products.py
remotior_sensus/tools/mosaic.py
remotior_sensus/tools/preprocess_products.py
remotior_sensus/tools/raster_edit.py
remotior_sensus/tools/raster_label.py
remotior_sensus/tools/raster_reclassification.py
remotior_sensus/tools/raster_report.py
remotior_sensus/tools/raster_split.py
remotior_sensus/tools/raster_to_vector.py
remotior_sensus/tools/raster_zonal_stats.py
remotior_sensus/tools/vector_to_raster.py
remotior_sensus/ui/jupyter.py
remotior_sensus/util/__init__.py
remotior_sensus/util/dates_times.py
remotior_sensus/util/download_tools.py
remotior_sensus/util/files_directories.py
remotior_sensus/util/plot_tools.py
remotior_sensus/util/pytorch_tools.py
remotior_sensus-0.5.2.dist-info/METADATA
remotior_sensus-0.5.2.dist-info/WHEEL
remotior_sensus-0.5.2.dist-info/licenses/COPYING
remotior_sensus-0.5.2.dist-info/licenses/LICENSE
remotior_sensus-0.5.2.dist-info/RECORD
