Metadata-Version: 2.4
Name: remotior_sensus
Version: 0.5.2
Summary: Remotior Sensus is software to process remote sensing and GIS data
Project-URL: Homepage, https://github.com/semiautomaticgit/remotior_sensus
Project-URL: Bug Tracker, https://github.com/semiautomaticgit/remotior_sensus/issues
Author-email: Luca Congedo <ing.congedoluca@gmail.com>
License-File: COPYING
License-File: LICENSE
Classifier: License :: OSI Approved :: GNU General Public License v3 or later (GPLv3+)
Classifier: Operating System :: OS Independent
Classifier: Programming Language :: Python :: 3
Classifier: Topic :: Scientific/Engineering :: GIS
Classifier: Topic :: Scientific/Engineering :: Image Processing
Requires-Python: >=3.8
